{"GlobalPropertiesHash":"Mu+tONa08Ac43+ZDyRUwGYwG6HJewY2XniBNfV/OQ3w=","FingerprintPatternsHash":"gq3WsqcKBUGTSNle7RKKyXRIwh7M8ccEqOqYvIzoM04=","PropertyOverridesHash":"8ZRc1sGeVrPBx4lD717BgRaQekyh78QKV9SKsdt638U=","InputHashes":["d1Kjamx3aoyzgsw5QoT/hjzzteUON9TpIPGhoqbUQog=","lMAn2gFCjA90V3RLAKEfhqQFFxRJl9yMBsXtOYZ1XqQ=","2GsMjCIJko4i95Mc8\u002Bm36DBcjYgQpBrQwhsQBAwYs/Q=","cPOqXzGYm/26gqcqoQVWJ764xlEh7Jmx7Kb\u002BSG8fZ8w=","FZsMZ7igY9GRWp\u002B99BHeRz4Tu\u002Bzu0wDBu11FaCYfCTI=","97U0F1tjlbq8Bgy/nFg/W\u002BozyY1C06/jgQLiNIi4wMo=","abZ2Bv2J8nHzYaW/CRI02UQRPx3m8VZUR1EXfOnIzLk=","7nJ6JFUf8gHqGho9SH\u002BDX4PKZk/rrbImoe\u002BSR1x/2e4=","4cTWc6O104ay0vw6qRAFvWGpDuVAq2Do4yX0cVBjlrA=","jKFhs\u002B9Oy80JQPAJOev9gwUemwiU59r9KtFpJpmV\u002BFQ=","ISzXfKyGLmFhcVKPSYv4sHcf8w6iGkRR6SXBM5B447s="],"CachedAssets":{"d1Kjamx3aoyzgsw5QoT/hjzzteUON9TpIPGhoqbUQog=":{"Identity":"C:\\Users\\DhuniPc0\\Desktop\\chat\\api\\wwwroot\\uploads\\17a39e7b-8c14-4f52-b843-1b90f6aa2e35.jpg","SourceId":"API","SourceType":"Discovered","ContentRoot":"C:\\Users\\DhuniPc0\\Desktop\\chat\\api\\wwwroot\\","BasePath":"_content/API","RelativePath":"uploads/17a39e7b-8c14-4f52-b843-1b90f6aa2e35#[.{fingerprint}]?.jpg","AssetKind":"All","AssetMode":"All","AssetRole":"Primary","AssetMergeBehavior":null,"AssetMergeSource":"","RelatedAsset":null,"AssetTraitName":null,"AssetTraitValue":null,"Fingerprint":"xr74zec6kz","Integrity":"XTuTNj0I9\u002BJK2UcfYtSUTLY1BLOlMe6P6boONFMAi28=","CopyToOutputDirectory":"Never","CopyToPublishDirectory":"PreserveNewest","OriginalItemSpec":"wwwroot\\uploads\\17a39e7b-8c14-4f52-b843-1b90f6aa2e35.jpg","FileLength":5184,"LastWriteTime":"2025-08-13T06:25:02.9624204+00:00"},"lMAn2gFCjA90V3RLAKEfhqQFFxRJl9yMBsXtOYZ1XqQ=":{"Identity":"C:\\Users\\DhuniPc0\\Desktop\\chat\\api\\wwwroot\\uploads\\37c5d765-c568-4b81-b510-28077f072847.jpg","SourceId":"API","SourceType":"Discovered","ContentRoot":"C:\\Users\\DhuniPc0\\Desktop\\chat\\api\\wwwroot\\","BasePath":"_content/API","RelativePath":"uploads/37c5d765-c568-4b81-b510-28077f072847#[.{fingerprint}]?.jpg","AssetKind":"All","AssetMode":"All","AssetRole":"Primary","AssetMergeBehavior":null,"AssetMergeSource":"","RelatedAsset":null,"AssetTraitName":null,"AssetTraitValue":null,"Fingerprint":"oycxz38iih","Integrity":"IFEIEZNhkNmb09PJSmBmwaaQrgjglYqY8l9LXiS/goo=","CopyToOutputDirectory":"Never","CopyToPublishDirectory":"PreserveNewest","OriginalItemSpec":"wwwroot\\uploads\\37c5d765-c568-4b81-b510-28077f072847.jpg","FileLength":7401,"LastWriteTime":"2025-08-21T04:12:53.4048846+00:00"},"2GsMjCIJko4i95Mc8\u002Bm36DBcjYgQpBrQwhsQBAwYs/Q=":{"Identity":"C:\\Users\\DhuniPc0\\Desktop\\chat\\api\\wwwroot\\uploads\\45d37a23-1015-48f5-8108-3d9484c20c1c.png","SourceId":"API","SourceType":"Discovered","ContentRoot":"C:\\Users\\DhuniPc0\\Desktop\\chat\\api\\wwwroot\\","BasePath":"_content/API","RelativePath":"uploads/45d37a23-1015-48f5-8108-3d9484c20c1c#[.{fingerprint}]?.png","AssetKind":"All","AssetMode":"All","AssetRole":"Primary","AssetMergeBehavior":null,"AssetMergeSource":"","RelatedAsset":null,"AssetTraitName":null,"AssetTraitValue":null,"Fingerprint":"w11unuy0jp","Integrity":"1C9pjvXfpZ1r5hEw9zbUziaLFF3yJryQe\u002B5A3up4GRI=","CopyToOutputDirectory":"Never","CopyToPublishDirectory":"PreserveNewest","OriginalItemSpec":"wwwroot\\uploads\\45d37a23-1015-48f5-8108-3d9484c20c1c.png","FileLength":143848,"LastWriteTime":"2025-08-18T02:44:49.7631104+00:00"},"cPOqXzGYm/26gqcqoQVWJ764xlEh7Jmx7Kb\u002BSG8fZ8w=":{"Identity":"C:\\Users\\DhuniPc0\\Desktop\\chat\\api\\wwwroot\\uploads\\5293e7dc-7c73-4058-8619-00f0d99b259f.jpg","SourceId":"API","SourceType":"Discovered","ContentRoot":"C:\\Users\\DhuniPc0\\Desktop\\chat\\api\\wwwroot\\","BasePath":"_content/API","RelativePath":"uploads/5293e7dc-7c73-4058-8619-00f0d99b259f#[.{fingerprint}]?.jpg","AssetKind":"All","AssetMode":"All","AssetRole":"Primary","AssetMergeBehavior":null,"AssetMergeSource":"","RelatedAsset":null,"AssetTraitName":null,"AssetTraitValue":null,"Fingerprint":"tyi1pmlxu0","Integrity":"u4gDr1mpWPCpUVZ9Z1A\u002BGcFQF31KUGjDvmMHEJt2TyQ=","CopyToOutputDirectory":"Never","CopyToPublishDirectory":"PreserveNewest","OriginalItemSpec":"wwwroot\\uploads\\5293e7dc-7c73-4058-8619-00f0d99b259f.jpg","FileLength":6827,"LastWriteTime":"2025-08-14T07:54:32.1557303+00:00"},"FZsMZ7igY9GRWp\u002B99BHeRz4Tu\u002Bzu0wDBu11FaCYfCTI=":{"Identity":"C:\\Users\\DhuniPc0\\Desktop\\chat\\api\\wwwroot\\uploads\\55711f97-3f7b-441c-916c-ede18e98ed3f.jpg","SourceId":"API","SourceType":"Discovered","ContentRoot":"C:\\Users\\DhuniPc0\\Desktop\\chat\\api\\wwwroot\\","BasePath":"_content/API","RelativePath":"uploads/55711f97-3f7b-441c-916c-ede18e98ed3f#[.{fingerprint}]?.jpg","AssetKind":"All","AssetMode":"All","AssetRole":"Primary","AssetMergeBehavior":null,"AssetMergeSource":"","RelatedAsset":null,"AssetTraitName":null,"AssetTraitValue":null,"Fingerprint":"xr74zec6kz","Integrity":"XTuTNj0I9\u002BJK2UcfYtSUTLY1BLOlMe6P6boONFMAi28=","CopyToOutputDirectory":"Never","CopyToPublishDirectory":"PreserveNewest","OriginalItemSpec":"wwwroot\\uploads\\55711f97-3f7b-441c-916c-ede18e98ed3f.jpg","FileLength":5184,"LastWriteTime":"2025-08-14T07:12:01.0691428+00:00"},"97U0F1tjlbq8Bgy/nFg/W\u002BozyY1C06/jgQLiNIi4wMo=":{"Identity":"C:\\Users\\DhuniPc0\\Desktop\\chat\\api\\wwwroot\\uploads\\b1d829f8-15d8-4b77-854a-366a72e07e67.jpg","SourceId":"API","SourceType":"Discovered","ContentRoot":"C:\\Users\\DhuniPc0\\Desktop\\chat\\api\\wwwroot\\","BasePath":"_content/API","RelativePath":"uploads/b1d829f8-15d8-4b77-854a-366a72e07e67#[.{fingerprint}]?.jpg","AssetKind":"All","AssetMode":"All","AssetRole":"Primary","AssetMergeBehavior":null,"AssetMergeSource":"","RelatedAsset":null,"AssetTraitName":null,"AssetTraitValue":null,"Fingerprint":"tyi1pmlxu0","Integrity":"u4gDr1mpWPCpUVZ9Z1A\u002BGcFQF31KUGjDvmMHEJt2TyQ=","CopyToOutputDirectory":"Never","CopyToPublishDirectory":"PreserveNewest","OriginalItemSpec":"wwwroot\\uploads\\b1d829f8-15d8-4b77-854a-366a72e07e67.jpg","FileLength":6827,"LastWriteTime":"2025-08-21T03:33:42.1850528+00:00"},"abZ2Bv2J8nHzYaW/CRI02UQRPx3m8VZUR1EXfOnIzLk=":{"Identity":"C:\\Users\\DhuniPc0\\Desktop\\chat\\api\\wwwroot\\uploads\\b58274c8-4ba5-4b2a-b781-65039b6c731f.png","SourceId":"API","SourceType":"Discovered","ContentRoot":"C:\\Users\\DhuniPc0\\Desktop\\chat\\api\\wwwroot\\","BasePath":"_content/API","RelativePath":"uploads/b58274c8-4ba5-4b2a-b781-65039b6c731f#[.{fingerprint}]?.png","AssetKind":"All","AssetMode":"All","AssetRole":"Primary","AssetMergeBehavior":null,"AssetMergeSource":"","RelatedAsset":null,"AssetTraitName":null,"AssetTraitValue":null,"Fingerprint":"w11unuy0jp","Integrity":"1C9pjvXfpZ1r5hEw9zbUziaLFF3yJryQe\u002B5A3up4GRI=","CopyToOutputDirectory":"Never","CopyToPublishDirectory":"PreserveNewest","OriginalItemSpec":"wwwroot\\uploads\\b58274c8-4ba5-4b2a-b781-65039b6c731f.png","FileLength":143848,"LastWriteTime":"2025-08-18T02:44:49.7631104+00:00"},"7nJ6JFUf8gHqGho9SH\u002BDX4PKZk/rrbImoe\u002BSR1x/2e4=":{"Identity":"C:\\Users\\DhuniPc0\\Desktop\\chat\\api\\wwwroot\\uploads\\bb75abb3-b73b-476d-b041-c9f3a58b71b4.jpg","SourceId":"API","SourceType":"Discovered","ContentRoot":"C:\\Users\\DhuniPc0\\Desktop\\chat\\api\\wwwroot\\","BasePath":"_content/API","RelativePath":"uploads/bb75abb3-b73b-476d-b041-c9f3a58b71b4#[.{fingerprint}]?.jpg","AssetKind":"All","AssetMode":"All","AssetRole":"Primary","AssetMergeBehavior":null,"AssetMergeSource":"","RelatedAsset":null,"AssetTraitName":null,"AssetTraitValue":null,"Fingerprint":"tyi1pmlxu0","Integrity":"u4gDr1mpWPCpUVZ9Z1A\u002BGcFQF31KUGjDvmMHEJt2TyQ=","CopyToOutputDirectory":"Never","CopyToPublishDirectory":"PreserveNewest","OriginalItemSpec":"wwwroot\\uploads\\bb75abb3-b73b-476d-b041-c9f3a58b71b4.jpg","FileLength":6827,"LastWriteTime":"2025-08-21T03:33:28.2150219+00:00"},"4cTWc6O104ay0vw6qRAFvWGpDuVAq2Do4yX0cVBjlrA=":{"Identity":"C:\\Users\\DhuniPc0\\Desktop\\chat\\api\\wwwroot\\uploads\\d960e9a1-7c83-4abf-8206-4c7a0466a7ce.jpg","SourceId":"API","SourceType":"Discovered","ContentRoot":"C:\\Users\\DhuniPc0\\Desktop\\chat\\api\\wwwroot\\","BasePath":"_content/API","RelativePath":"uploads/d960e9a1-7c83-4abf-8206-4c7a0466a7ce#[.{fingerprint}]?.jpg","AssetKind":"All","AssetMode":"All","AssetRole":"Primary","AssetMergeBehavior":null,"AssetMergeSource":"","RelatedAsset":null,"AssetTraitName":null,"AssetTraitValue":null,"Fingerprint":"42jy0esvw7","Integrity":"BPMmrhl7tvO31ihK4EIjeaLbkOMxBvrXklm7OgUaPzY=","CopyToOutputDirectory":"Never","CopyToPublishDirectory":"PreserveNewest","OriginalItemSpec":"wwwroot\\uploads\\d960e9a1-7c83-4abf-8206-4c7a0466a7ce.jpg","FileLength":118916,"LastWriteTime":"2025-08-21T04:37:42.2439025+00:00"}},"CachedCopyCandidates":{}}